{
  "defaultLanguage" : "en-US",
  "defaultPrice" : {
    "currency" : "USD",
    "priceMicros" : "2000000"
  },
  "listings" : {
    "en-US" : {
      "description" : "I mean it - pay what you want get access to all pro-features! ",
      "title" : "Supporter 2019 - Ground Crew"
    }
  },
  "packageName" : "me.calebjones.spacelaunchnow",
  "prices" : {
    "DZ" : {
      "currency" : "DZD",
      "priceMicros" : "250000000"
    },
    "AU" : {
      "currency" : "AUD",
      "priceMicros" : "3190000"
    },
    "AT" : {
      "currency" : "EUR",
      "priceMicros" : "2190000"
    },
    "BH" : {
      "currency" : "USD",
      "priceMicros" : "1990000"
    },
    "BD" : {
      "currency" : "BDT",
      "priceMicros" : "150000000"
    },
    "BE" : {
      "currency" : "EUR",
      "priceMicros" : "2190000"
    },
    "BM" : {
      "currency" : "USD",
      "priceMicros" : "1990000"
    },
    "BO" : {
      "currency" : "BOB",
      "priceMicros" : "13990000"
    },
    "BR" : {
      "currency" : "BRL",
      "priceMicros" : "7990000"
    },
    "VG" : {
      "currency" : "USD",
      "priceMicros" : "1990000"
    },
    "BG" : {
      "currency" : "BGN",
      "priceMicros" : "4190000"
    },
    "KH" : {
      "currency" : "USD",
      "priceMicros" : "1990000"
    },
    "CA" : {
      "currency" : "CAD",
      "priceMicros" : "2690000"
    },
    "KY" : {
      "currency" : "USD",
      "priceMicros" : "1990000"
    },
    "CL" : {
      "currency" : "CLP",
      "priceMicros" : "1400000000"
    },
    "CO" : {
      "currency" : "COP",
      "priceMicros" : "6500000000"
    },
    "CR" : {
      "currency" : "CRC",
      "priceMicros" : "1200000000"
    },
    "HR" : {
      "currency" : "HRK",
      "priceMicros" : "17000000"
    },
    "CY" : {
      "currency" : "EUR",
      "priceMicros" : "2090000"
    },
    "CZ" : {
      "currency" : "CZK",
      "priceMicros" : "54990000"
    },
    "DK" : {
      "currency" : "DKK",
      "priceMicros" : "17000000"
    },
    "EG" : {
      "currency" : "EGP",
      "priceMicros" : "33990000"
    },
    "EE" : {
      "currency" : "EUR",
      "priceMicros" : "2190000"
    },
    "FI" : {
      "currency" : "EUR",
      "priceMicros" : "2190000"
    },
    "FR" : {
      "currency" : "EUR",
      "priceMicros" : "2190000"
    },
    "GE" : {
      "currency" : "GEL",
      "priceMicros" : "5000000"
    },
    "DE" : {
      "currency" : "EUR",
      "priceMicros" : "2090000"
    },
    "GH" : {
      "currency" : "GHS",
      "priceMicros" : "10000000"
    },
    "GR" : {
      "currency" : "EUR",
      "priceMicros" : "2190000"
    },
    "HK" : {
      "currency" : "HKD",
      "priceMicros" : "15000000"
    },
    "HU" : {
      "currency" : "HUF",
      "priceMicros" : "699000000"
    },
    "IN" : {
      "currency" : "INR",
      "priceMicros" : "170000000"
    },
    "ID" : {
      "currency" : "IDR",
      "priceMicros" : "29000000000"
    },
    "IQ" : {
      "currency" : "IQD",
      "priceMicros" : "2400000000"
    },
    "IE" : {
      "currency" : "EUR",
      "priceMicros" : "2190000"
    },
    "IL" : {
      "currency" : "ILS",
      "priceMicros" : "7100000"
    },
    "IT" : {
      "currency" : "EUR",
      "priceMicros" : "2190000"
    },
    "JP" : {
      "currency" : "JPY",
      "priceMicros" : "220000000"
    },
    "JO" : {
      "currency" : "JOD",
      "priceMicros" : "1400000"
    },
    "KZ" : {
      "currency" : "KZT",
      "priceMicros" : "790000000"
    },
    "KE" : {
      "currency" : "KES",
      "priceMicros" : "200000000"
    },
    "KW" : {
      "currency" : "USD",
      "priceMicros" : "1990000"
    },
    "LV" : {
      "currency" : "EUR",
      "priceMicros" : "2190000"
    },
    "LB" : {
      "currency" : "LBP",
      "priceMicros" : "3000000000"
    },
    "LI" : {
      "currency" : "CHF",
      "priceMicros" : "2000000"
    },
    "LT" : {
      "currency" : "EUR",
      "priceMicros" : "2190000"
    },
    "LU" : {
      "currency" : "EUR",
      "priceMicros" : "2090000"
    },
    "MO" : {
      "currency" : "MOP",
      "priceMicros" : "15990000"
    },
    "MY" : {
      "currency" : "MYR",
      "priceMicros" : "8490000"
    },
    "MX" : {
      "currency" : "MXN",
      "priceMicros" : "38000000"
    },
    "MA" : {
      "currency" : "MAD",
      "priceMicros" : "18990000"
    },
    "MM" : {
      "currency" : "MMK",
      "priceMicros" : "3000000000"
    },
    "NL" : {
      "currency" : "EUR",
      "priceMicros" : "2190000"
    },
    "NZ" : {
      "currency" : "NZD",
      "priceMicros" : "3490000"
    },
    "NG" : {
      "currency" : "NGN",
      "priceMicros" : "720000000"
    },
    "NO" : {
      "currency" : "NOK",
      "priceMicros" : "22000000"
    },
    "OM" : {
      "currency" : "USD",
      "priceMicros" : "1990000"
    },
    "PK" : {
      "currency" : "PKR",
      "priceMicros" : "300000000"
    },
    "PY" : {
      "currency" : "PYG",
      "priceMicros" : "10000000000"
    },
    "PE" : {
      "currency" : "PEN",
      "priceMicros" : "6490000"
    },
    "PH" : {
      "currency" : "PHP",
      "priceMicros" : "105000000"
    },
    "PL" : {
      "currency" : "PLN",
      "priceMicros" : "9490000"
    },
    "PT" : {
      "currency" : "EUR",
      "priceMicros" : "2190000"
    },
    "QA" : {
      "currency" : "QAR",
      "priceMicros" : "7500000"
    },
    "RO" : {
      "currency" : "RON",
      "priceMicros" : "9990000"
    },
    "RU" : {
      "currency" : "RUB",
      "priceMicros" : "159000000"
    },
    "SA" : {
      "currency" : "SAR",
      "priceMicros" : "7890000"
    },
    "RS" : {
      "currency" : "RSD",
      "priceMicros" : "249000000"
    },
    "SG" : {
      "currency" : "SGD",
      "priceMicros" : "2980000"
    },
    "SK" : {
      "currency" : "EUR",
      "priceMicros" : "2190000"
    },
    "SI" : {
      "currency" : "EUR",
      "priceMicros" : "2190000"
    },
    "ZA" : {
      "currency" : "ZAR",
      "priceMicros" : "28990000"
    },
    "KR" : {
      "currency" : "KRW",
      "priceMicros" : "2600000000"
    },
    "ES" : {
      "currency" : "EUR",
      "priceMicros" : "2190000"
    },
    "LK" : {
      "currency" : "LKR",
      "priceMicros" : "350000000"
    },
    "SE" : {
      "currency" : "SEK",
      "priceMicros" : "24000000"
    },
    "CH" : {
      "currency" : "CHF",
      "priceMicros" : "2000000"
    },
    "TW" : {
      "currency" : "TWD",
      "priceMicros" : "66000000"
    },
    "TZ" : {
      "currency" : "TZS",
      "priceMicros" : "4600000000"
    },
    "TH" : {
      "currency" : "THB",
      "priceMicros" : "64000000"
    },
    "TR" : {
      "currency" : "TRY",
      "priceMicros" : "13990000"
    },
    "TC" : {
      "currency" : "USD",
      "priceMicros" : "1990000"
    },
    "UA" : {
      "currency" : "UAH",
      "priceMicros" : "54990000"
    },
    "AE" : {
      "currency" : "AED",
      "priceMicros" : "7690000"
    },
    "GB" : {
      "currency" : "GBP",
      "priceMicros" : "1890000"
    },
    "US" : {
      "currency" : "USD",
      "priceMicros" : "1990000"
    },
    "VN" : {
      "currency" : "VND",
      "priceMicros" : "47000000000"
    }
  },
  "purchaseType" : "managedUser",
  "sku" : "2019_two_dollar_support",
  "status" : "inactive"
}
